bm3d/__init__.py
bm3d/profiles.py
bm3d-4.0.2.dist-info/LICENSE
bm3d-4.0.2.dist-info/METADATA
bm3d-4.0.2.dist-info/WHEEL
bm3d-4.0.2.dist-info/top_level.txt
bm3d-4.0.2.dist-info/RECORD
