Metadata-Version: 2.1
Name: bm3d
Version: 4.0.2
Summary: BM3D for correlated noise
Home-page: https://webpages.tuni.fi/foi/GCF-BM3D/
Author: Ymir Mäkinen
Author-email: ymir.makinen@tuni.fi
Classifier: Development Status :: 3 - Alpha
Classifier: License :: Free for non-commercial use
Classifier: Intended Audience :: Education
Classifier: Intended Audience :: Science/Research
Classifier: Operating System :: POSIX :: Linux
Classifier: Operating System :: Microsoft :: Windows
Classifier: Operating System :: MacOS
Classifier: Programming Language :: Python :: 3
Classifier: Topic :: Scientific/Engineering :: Information Analysis
Classifier: Topic :: Scientific/Engineering :: Mathematics
Classifier: Topic :: Software Development :: Libraries :: Python Modules
Requires-Python: >=3.5
License-File: LICENSE
Requires-Dist: bm4d >=4.2.4
